opensearch_service/__init__.py
opensearch_service/opensearch_service.py
opensearch_service-0.23.dist-info/METADATA
opensearch_service-0.23.dist-info/WHEEL
opensearch_service-0.23.dist-info/top_level.txt
opensearch_service-0.23.dist-info/RECORD
