Metadata-Version: 2.1
Name: opensearch-service
Version: 0.23
Summary: easy access to OpenSearch based on opensearch-dsl
Home-page: https://github.com/bertrandchevrier/opensearch-service.git
Author: The data handyman team
Author-email: chevrierbertrand@yahoo.fr
License: MIT
Platform: UNKNOWN
Classifier: Development Status :: 3 - Alpha
Requires-Python: >=3.5
Requires-Dist: opensearch
Requires-Dist: opensearch-dsl
Requires-Dist: pandas
